.travis.yml
AUTHORS.rst
CHANGES.rst
COPYING.txt
MANIFEST.in
README.rst
development.ini
runtests.py
setup.cfg
setup.py
kotti_contactform/__init__.py
kotti_contactform/populate.py
kotti_contactform/resources.py
kotti_contactform/views.py
kotti_contactform/widgets.py
kotti_contactform.egg-info/PKG-INFO
kotti_contactform.egg-info/SOURCES.txt
kotti_contactform.egg-info/dependency_links.txt
kotti_contactform.egg-info/not-zip-safe
kotti_contactform.egg-info/requires.txt
kotti_contactform.egg-info/top_level.txt
kotti_contactform/alembic/script.py.mako
kotti_contactform/alembic/versions/244d976e5f57_add_column_sender.py
kotti_contactform/alembic/versions/39ded03760da_add_column_show_atta.py
kotti_contactform/locale/kotti_contactform.pot
kotti_contactform/locale/de/LC_MESSAGES/kotti_contactform.mo
kotti_contactform/locale/de/LC_MESSAGES/kotti_contactform.po
kotti_contactform/locale/fr/LC_MESSAGES/kotti_contactform.mo
kotti_contactform/locale/fr/LC_MESSAGES/kotti_contactform.po
kotti_contactform/locale/ja/LC_MESSAGES/kotti_contactform.mo
kotti_contactform/locale/ja/LC_MESSAGES/kotti_contactform.po
kotti_contactform/locale/ro/LC_MESSAGES/kotti_contactform.mo
kotti_contactform/locale/ro/LC_MESSAGES/kotti_contactform.po
kotti_contactform/templates/contactform-view-one-column.pt
kotti_contactform/templates/contactform-view-two-columns.pt
kotti_contactform/templates/recaptcha_widget.pt
kotti_contactform/tests/browser.txt
kotti_contactform/tests/test_widgets.py