Metadata-Version: 1.1
Name: kotti-contactform
Version: 0.5.1
Summary: Simple contact form for Kotti sites
Home-page: https://github.com/Kotti/kotti_contactform
Author: Kotti developers
Author-email: kotti@googlegroups.com
License: BSD-2-Clause
Keywords: kotti contact form
Platform: UNKNOWN
Classifier: Development Status :: 4 - Beta
Classifier: Programming Language :: Python
Classifier: Framework :: Pylons
Classifier: Topic :: Internet :: WWW/HTTP
Classifier: Topic :: Internet :: WWW/HTTP :: Dynamic Content
Classifier: Topic :: Internet :: WWW/HTTP :: WSGI :: Application
Classifier: License :: OSI Approved :: BSD License
